GhoslInk/__init__.py
GhoslInk/ghostink.py
GhoslInk/testing.py
GhoslInk/tests/__init__.py
GhoslInk/tests/test_ghostink.py
ghostink/__init__.py
ghostink/ghostink.py
ghostink/main.py
ghostink/testing.py
ghostink/tests/__init__.py
ghostink/tests/test_ghostink.py
taskara/__init__.py
taskara/taskara.py
taskara/testing.py
taskara/tests/__init__.py
taskara/tests/test_taskara.py
taskaraCore/__init__.py
taskaraCore/taskara.py
taskaraCore/taskaraCore.py
taskaraCore/testing.py
taskaraCore/tests/__init__.py
taskaraCore/tests/test_taskara.py
GhoslInk-0.0.1.dist-info/LICENSE
GhoslInk-0.0.1.dist-info/METADATA
GhoslInk-0.0.1.dist-info/WHEEL
GhoslInk-0.0.1.dist-info/top_level.txt
GhoslInk-0.0.1.dist-info/RECORD
